<?xml version="1.0" encoding="UTF-8"?>
<Tracks nTracks="3" spaceUnits="pixel" frameInterval="1.0" timeUnits="frame" generationDateTime="vr, 20 dec 2024 16:36:15" from="TrackMate v7.13.2">
  <particle nSpots="458">
    <detection t="0" x="334.04248443348746" y="295.5368112511435" z="0.0" />
    <detection t="1" x="333.14982221974617" y="295.4838092797504" z="0.0" />
    <detection t="2" x="333.9083511882801" y="295.0590830063079" z="0.0" />
    <detection t="3" x="333.8686624273494" y="295.1530526283341" z="0.0" />
    <detection t="4" x="333.83509389486255" y="294.8428029512454" z="0.0" />
    <detection t="5" x="333.8553540853308" y="295.6138158533281" z="0.0" />
    <detection t="6" x="335.01174047281336" y="294.7149691248197" z="0.0" />
    <detection t="7" x="334.3990674422683" y="295.8563908267419" z="0.0" />
    <detection t="8" x="333.5154075591864" y="294.95099544477705" z="0.0" />
    <detection t="9" x="333.5466202966804" y="295.8492002109899" z="0.0" />
    <detection t="10" x="334.00033165188313" y="295.5316946449807" z="0.0" />
    <detection t="11" x="333.913289924938" y="295.67080234431245" z="0.0" />
    <detection t="12" x="334.0940267407437" y="295.2025875988117" z="0.0" />
    <detection t="13" x="334.2066926674707" y="295.0495268247014" z="0.0" />
    <detection t="14" x="333.1172118402915" y="295.2957846132453" z="0.0" />
    <detection t="15" x="332.8222543705736" y="295.07444172210165" z="0.0" />
    <detection t="16" x="333.6266055204585" y="294.35808185687335" z="0.0" />
    <detection t="17" x="333.7276904147467" y="294.84886931197826" z="0.0" />
    <detection t="18" x="333.7339865528795" y="295.2211290611302" z="0.0" />
    <detection t="19" x="333.28868597687244" y="294.9293397613698" z="0.0" />
    <detection t="20" x="333.95601066378" y="295.0236756132941" z="0.0" />
    <detection t="21" x="334.37064659508997" y="295.2136741193837" z="0.0" />
    <detection t="22" x="334.630046725117" y="295.6730123322004" z="0.0" />
    <detection t="23" x="334.35301370534734" y="295.7678034704846" z="0.0" />
    <detection t="24" x="334.8308066195939" y="295.35231371590237" z="0.0" />
    <detection t="25" x="333.73654359316447" y="294.395180915553" z="0.0" />
    <detection t="26" x="334.2797058991417" y="294.2838374863697" z="0.0" />
    <detection t="27" x="333.7252161212201" y="295.3447544252548" z="0.0" />
    <detection t="28" x="332.99263995343796" y="295.76316186279007" z="0.0" />
    <detection t="29" x="333.4891786053238" y="295.4720535483795" z="0.0" />
    <detection t="30" x="333.7142490010325" y="294.91182971477116" z="0.0" />
    <detection t="31" x="334.20474953792586" y="295.41536462531883" z="0.0" />
    <detection t="32" x="334.20146394578643" y="295.43078550501014" z="0.0" />
    <detection t="33" x="333.4116730901715" y="295.112509041329" z="0.0" />
    <detection t="34" x="334.30525300477404" y="295.15660989848345" z="0.0" />
    <detection t="35" x="333.3626402102709" y="295.0455938721101" z="0.0" />
    <detection t="36" x="334.130833893479" y="294.82355243096526" z="0.0" />
    <detection t="37" x="333.67812201081443" y="294.8814499194858" z="0.0" />
    <detection t="38" x="332.19296706153597" y="295.2656241446731" z="0.0" />
    <detection t="39" x="333.13341459740786" y="294.85322105918726" z="0.0" />
    <detection t="40" x="334.16171447260507" y="294.6577677995807" z="0.0" />
    <detection t="41" x="333.95313759320896" y="294.81992864854885" z="0.0" />
    <detection t="42" x="333.61697823629913" y="294.84744289865904" z="0.0" />
    <detection t="43" x="333.85387421767774" y="295.42715238517206" z="0.0" />
    <detection t="44" x="333.1345037852074" y="296.0338898591831" z="0.0" />
    <detection t="45" x="333.8151403756434" y="295.04444817074085" z="0.0" />
    <detection t="46" x="333.1225509011664" y="295.08070950163705" z="0.0" />
    <detection t="47" x="333.8407551715455" y="295.6592052690617" z="0.0" />
    <detection t="48" x="333.8702783323302" y="295.6671663925908" z="0.0" />
    <detection t="49" x="333.956025257525" y="295.89554467613067" z="0.0" />
    <detection t="50" x="332.62135271562573" y="296.2356717248675" z="0.0" />
    <detection t="51" x="333.13516394231317" y="296.25817485074924" z="0.0" />
    <detection t="52" x="332.32406098747214" y="295.85287228473805" z="0.0" />
    <detection t="53" x="332.4316006144752" y="295.8253291784689" z="0.0" />
    <detection t="54" x="332.1987286454883" y="295.7044324277649" z="0.0" />
    <detection t="55" x="332.80111476846673" y="296.32843398373734" z="0.0" />
    <detection t="56" x="332.17588812961975" y="295.81948422132274" z="0.0" />
    <detection t="57" x="332.46309497321" y="296.0323261333553" z="0.0" />
    <detection t="58" x="332.3375821720023" y="296.0575519059333" z="0.0" />
    <detection t="59" x="332.01096564456736" y="296.243356033259" z="0.0" />
    <detection t="60" x="332.4557682520677" y="295.9426770809638" z="0.0" />
    <detection t="61" x="332.0051487188536" y="295.2345366146204" z="0.0" />
    <detection t="62" x="332.369185304836" y="295.72457025953963" z="0.0" />
    <detection t="63" x="332.39411899160837" y="294.8359604693185" z="0.0" />
    <detection t="64" x="331.5721829154207" y="295.08611324537594" z="0.0" />
    <detection t="65" x="332.81486543581093" y="294.82033673652455" z="0.0" />
    <detection t="66" x="332.6040685685837" y="295.3345032494699" z="0.0" />
    <detection t="67" x="331.6432946196515" y="294.77236332125403" z="0.0" />
    <detection t="68" x="332.04184886897986" y="295.7671297318218" z="0.0" />
    <detection t="69" x="332.0909710257469" y="296.5873235453922" z="0.0" />
    <detection t="70" x="331.32040369658523" y="295.62894465170245" z="0.0" />
    <detection t="71" x="332.04686589625214" y="295.1697344609215" z="0.0" />
    <detection t="72" x="331.75642733637403" y="295.3932377349894" z="0.0" />
    <detection t="73" x="331.2139559237556" y="295.06212268365624" z="0.0" />
    <detection t="74" x="331.14313444416734" y="294.1983599290068" z="0.0" />
    <detection t="75" x="332.2227746935724" y="295.330985199075" z="0.0" />
    <detection t="76" x="332.28984365025514" y="295.24449471225165" z="0.0" />
    <detection t="77" x="332.4502858412763" y="295.14705935216847" z="0.0" />
    <detection t="78" x="332.3101137428701" y="295.21597306007004" z="0.0" />
    <detection t="79" x="331.74713650894216" y="295.83809953804473" z="0.0" />
    <detection t="80" x="332.7414334101131" y="295.53520183226" z="0.0" />
    <detection t="81" x="332.40656463223667" y="294.7463390906762" z="0.0" />
    <detection t="82" x="332.8706792245483" y="295.92029622501224" z="0.0" />
    <detection t="83" x="332.6112850850075" y="295.6761820777467" z="0.0" />
    <detection t="84" x="332.8546906157699" y="295.55736020950445" z="0.0" />
    <detection t="85" x="331.9835271897587" y="295.89729138357217" z="0.0" />
    <detection t="86" x="331.89678041393756" y="295.60785420701814" z="0.0" />
    <detection t="87" x="332.20217200612285" y="295.3571871800338" z="0.0" />
    <detection t="88" x="331.4710902699516" y="295.2294731865445" z="0.0" />
    <detection t="89" x="331.905743361781" y="294.64646235660575" z="0.0" />
    <detection t="90" x="332.41431151075204" y="295.2679874211743" z="0.0" />
    <detection t="91" x="332.2358364965889" y="294.2014517310183" z="0.0" />
    <detection t="92" x="332.5087978185025" y="294.3827749530208" z="0.0" />
    <detection t="93" x="332.2844679650006" y="295.1205542569392" z="0.0" />
    <detection t="94" x="332.1773570272765" y="294.96981883001337" z="0.0" />
    <detection t="95" x="332.0158010605733" y="294.74004752628866" z="0.0" />
    <detection t="96" x="331.6655005720424" y="293.88254903861684" z="0.0" />
    <detection t="97" x="331.49458763986325" y="294.069921122155" z="0.0" />
    <detection t="98" x="331.16789106464427" y="293.218076808657" z="0.0" />
    <detection t="99" x="330.7814116314437" y="294.2384383572809" z="0.0" />
    <detection t="100" x="331.31067552466953" y="292.70267060435975" z="0.0" />
    <detection t="101" x="331.95774400776946" y="293.84180837126587" z="0.0" />
    <detection t="102" x="331.48139466603726" y="293.2858903107625" z="0.0" />
    <detection t="103" x="331.9974175334089" y="294.15846190059847" z="0.0" />
    <detection t="104" x="331.19399616101293" y="294.0991579019468" z="0.0" />
    <detection t="105" x="331.2000249459729" y="293.66479034366535" z="0.0" />
    <detection t="106" x="331.7465512994552" y="293.4384289819195" z="0.0" />
    <detection t="107" x="332.3532096607519" y="293.5118228760948" z="0.0" />
    <detection t="108" x="332.28335521616407" y="293.93523687102504" z="0.0" />
    <detection t="109" x="332.7220708983283" y="293.37691782848805" z="0.0" />
    <detection t="110" x="332.81770848282383" y="293.6375863436069" z="0.0" />
    <detection t="111" x="332.87575343401113" y="293.84682110973074" z="0.0" />
    <detection t="112" x="332.1880251447466" y="293.94924971185327" z="0.0" />
    <detection t="113" x="332.42328088156654" y="295.2583607270211" z="0.0" />
    <detection t="114" x="333.48621191534795" y="294.47353335026486" z="0.0" />
    <detection t="115" x="332.5801994128537" y="293.15315817318276" z="0.0" />
    <detection t="116" x="333.45507756967913" y="294.6882395206008" z="0.0" />
    <detection t="117" x="332.9062809855758" y="294.31731945326385" z="0.0" />
    <detection t="118" x="333.4623690526606" y="294.3447067297594" z="0.0" />
    <detection t="119" x="332.2998925922241" y="294.26477917494447" z="0.0" />
    <detection t="120" x="333.1610627805891" y="295.0665466881487" z="0.0" />
    <detection t="121" x="333.2898825538679" y="295.2074028429124" z="0.0" />
    <detection t="122" x="333.48804628632223" y="295.13186440957367" z="0.0" />
    <detection t="123" x="333.4941821788186" y="295.4790213059881" z="0.0" />
    <detection t="124" x="333.0955489767699" y="295.01751603265217" z="0.0" />
    <detection t="125" x="332.6858350821325" y="295.09469563431645" z="0.0" />
    <detection t="126" x="333.4193346493646" y="295.0969396424152" z="0.0" />
    <detection t="127" x="333.0763220017051" y="295.27680998242346" z="0.0" />
    <detection t="128" x="333.9668402452467" y="296.3139722255364" z="0.0" />
    <detection t="129" x="332.66769194167455" y="295.4489922884474" z="0.0" />
    <detection t="130" x="333.66042945901296" y="294.94324935331093" z="0.0" />
    <detection t="131" x="333.7012908842828" y="294.82226712854634" z="0.0" />
    <detection t="132" x="332.59205400828813" y="295.0105376865405" z="0.0" />
    <detection t="133" x="332.3809129630038" y="293.8149241082164" z="0.0" />
    <detection t="134" x="332.90218851455126" y="294.3001659748053" z="0.0" />
    <detection t="135" x="332.14906642319033" y="294.2042514300763" z="0.0" />
    <detection t="136" x="332.80527013782853" y="294.6345586147834" z="0.0" />
    <detection t="137" x="332.0389539820231" y="294.4671081766442" z="0.0" />
    <detection t="139" x="332.1277571925477" y="294.31602161312884" z="0.0" />
    <detection t="140" x="331.8152382427311" y="294.506078633816" z="0.0" />
    <detection t="141" x="333.08720287387274" y="295.3117178118477" z="0.0" />
    <detection t="142" x="332.52174382206164" y="294.5129588489469" z="0.0" />
    <detection t="143" x="332.61203539551843" y="294.6337099700213" z="0.0" />
    <detection t="144" x="331.96459070243344" y="294.8839198641975" z="0.0" />
    <detection t="145" x="332.34756025449747" y="294.41991007962724" z="0.0" />
    <detection t="146" x="332.7147338105386" y="293.91321735857866" z="0.0" />
    <detection t="147" x="332.6549640505026" y="294.34845625502106" z="0.0" />
    <detection t="148" x="332.27244595724187" y="293.94537024549084" z="0.0" />
    <detection t="149" x="332.2490274575688" y="294.9568932444706" z="0.0" />
    <detection t="150" x="331.7732490487322" y="293.7833230772596" z="0.0" />
    <detection t="151" x="331.64594172231534" y="294.8910137880827" z="0.0" />
    <detection t="152" x="331.1893726158493" y="295.019416088025" z="0.0" />
    <detection t="153" x="331.2511131472409" y="294.78568548098843" z="0.0" />
    <detection t="154" x="331.59975761892446" y="294.9678319766276" z="0.0" />
    <detection t="155" x="331.73793778604875" y="294.0828350840804" z="0.0" />
    <detection t="156" x="331.39700486970986" y="294.8541977337512" z="0.0" />
    <detection t="157" x="330.4543045492394" y="294.78852521215526" z="0.0" />
    <detection t="158" x="331.88076029731394" y="294.4644198972539" z="0.0" />
    <detection t="159" x="331.18430617955687" y="294.469021117153" z="0.0" />
    <detection t="160" x="331.8328972010652" y="294.40139480177857" z="0.0" />
    <detection t="161" x="330.7292440889994" y="295.13745057198923" z="0.0" />
    <detection t="162" x="330.3620323059897" y="294.98794770573153" z="0.0" />
    <detection t="163" x="329.8742111981039" y="294.6523952448573" z="0.0" />
    <detection t="164" x="330.4016238288187" y="294.4772000452617" z="0.0" />
    <detection t="165" x="329.8229005846229" y="295.078921884723" z="0.0" />
    <detection t="166" x="331.2821053822428" y="294.3655973564583" z="0.0" />
    <detection t="167" x="330.9674188003064" y="294.1362467554275" z="0.0" />
    <detection t="168" x="330.27074358489494" y="294.8370152526291" z="0.0" />
    <detection t="169" x="330.21112156149826" y="293.84439268822223" z="0.0" />
    <detection t="170" x="330.50684257179313" y="293.610520852574" z="0.0" />
    <detection t="171" x="330.4182331058584" y="293.8641838043093" z="0.0" />
    <detection t="172" x="330.09789222864794" y="294.6074211264206" z="0.0" />
    <detection t="173" x="331.43748460322183" y="293.36183659568076" z="0.0" />
    <detection t="174" x="329.40121140150984" y="293.975609342779" z="0.0" />
    <detection t="175" x="330.1407111751444" y="293.51453640282773" z="0.0" />
    <detection t="176" x="329.83802135048296" y="294.3857769055444" z="0.0" />
    <detection t="177" x="330.0747290924043" y="294.24522650116415" z="0.0" />
    <detection t="178" x="329.68609456580504" y="294.49223579649" z="0.0" />
    <detection t="179" x="329.49088696269644" y="294.4532483053923" z="0.0" />
    <detection t="180" x="330.00235307267394" y="294.21419288268515" z="0.0" />
    <detection t="181" x="329.7616320947655" y="294.17127039283866" z="0.0" />
    <detection t="182" x="330.01055184522534" y="294.3463360094824" z="0.0" />
    <detection t="183" x="330.725154190123" y="294.43537159796716" z="0.0" />
    <detection t="184" x="330.3218090918969" y="294.2023861320712" z="0.0" />
    <detection t="185" x="330.4988579674907" y="293.79617779811633" z="0.0" />
    <detection t="186" x="330.59907338442326" y="294.5039128632399" z="0.0" />
    <detection t="187" x="331.2690874262099" y="294.70682480665033" z="0.0" />
    <detection t="188" x="331.57791038320255" y="293.1578893969046" z="0.0" />
    <detection t="189" x="330.97548227787905" y="293.2340488986798" z="0.0" />
    <detection t="190" x="331.0816006296305" y="293.54728908904247" z="0.0" />
    <detection t="191" x="330.45354561435244" y="292.8946669362633" z="0.0" />
    <detection t="192" x="331.1030332854618" y="293.1136939791515" z="0.0" />
    <detection t="193" x="330.75602832005296" y="292.5809233996077" z="0.0" />
    <detection t="194" x="330.953535406047" y="293.0650811441377" z="0.0" />
    <detection t="195" x="331.10891850209697" y="293.16103478219173" z="0.0" />
    <detection t="196" x="330.9877691534716" y="294.06188575202833" z="0.0" />
    <detection t="197" x="331.3517346464197" y="294.3799847989914" z="0.0" />
    <detection t="198" x="330.9226582819969" y="293.590944169085" z="0.0" />
    <detection t="199" x="331.05646163623595" y="293.69596619488465" z="0.0" />
    <detection t="200" x="330.5729994562141" y="293.7126077777483" z="0.0" />
    <detection t="201" x="330.6309102156132" y="293.55299697913034" z="0.0" />
    <detection t="202" x="331.33985960212095" y="293.023406837915" z="0.0" />
    <detection t="203" x="330.53569451496867" y="292.6894641499898" z="0.0" />
    <detection t="204" x="331.1109610987565" y="293.1322420509019" z="0.0" />
    <detection t="205" x="331.16595733406643" y="293.26407321763753" z="0.0" />
    <detection t="206" x="331.20825603718356" y="293.4942090475046" z="0.0" />
    <detection t="207" x="330.95961545122486" y="293.5557780834002" z="0.0" />
    <detection t="208" x="331.4996574052604" y="293.49716340010434" z="0.0" />
    <detection t="209" x="330.96924142965" y="293.3469539754446" z="0.0" />
    <detection t="210" x="330.71319888617535" y="293.6963447099339" z="0.0" />
    <detection t="211" x="331.16181606409464" y="293.6607091916215" z="0.0" />
    <detection t="212" x="331.3169625901968" y="293.140100514431" z="0.0" />
    <detection t="213" x="331.72794535250614" y="293.9822557565773" z="0.0" />
    <detection t="214" x="331.8805039090607" y="293.5066495557913" z="0.0" />
    <detection t="215" x="331.8334740306955" y="293.55375622468114" z="0.0" />
    <detection t="216" x="332.1830825592715" y="293.88294652118805" z="0.0" />
    <detection t="217" x="332.37453804240204" y="293.7198351250212" z="0.0" />
    <detection t="218" x="331.5174478845272" y="293.8303414833717" z="0.0" />
    <detection t="219" x="332.5319366225298" y="293.07633207546667" z="0.0" />
    <detection t="220" x="331.31241247154054" y="294.05517881621796" z="0.0" />
    <detection t="221" x="331.6858998474874" y="294.344863744431" z="0.0" />
    <detection t="222" x="332.2478338110385" y="294.6037837506893" z="0.0" />
    <detection t="223" x="331.4009069540421" y="294.6313841808865" z="0.0" />
    <detection t="224" x="331.1568460757337" y="294.57702432886185" z="0.0" />
    <detection t="225" x="332.0068524538356" y="295.0381220007742" z="0.0" />
    <detection t="226" x="332.0243082842" y="295.2645819297879" z="0.0" />
    <detection t="227" x="331.9164427514612" y="295.3116585114559" z="0.0" />
    <detection t="228" x="331.3290799556462" y="295.5146557535109" z="0.0" />
    <detection t="229" x="332.0309584728169" y="295.0014089119989" z="0.0" />
    <detection t="230" x="331.7617671003877" y="295.23596393746004" z="0.0" />
    <detection t="231" x="332.254232504679" y="295.07527134744106" z="0.0" />
    <detection t="232" x="331.47206840761083" y="294.39184546028116" z="0.0" />
    <detection t="233" x="332.212384870042" y="294.1529092945094" z="0.0" />
    <detection t="234" x="331.46827595654713" y="294.4642391165309" z="0.0" />
    <detection t="235" x="332.3302884143515" y="293.7324178079183" z="0.0" />
    <detection t="236" x="332.11870730431934" y="293.6877266392758" z="0.0" />
    <detection t="237" x="331.5124604598452" y="294.3073430815799" z="0.0" />
    <detection t="238" x="331.5036122659629" y="294.3713079736604" z="0.0" />
    <detection t="239" x="331.5048116655223" y="293.53218267330107" z="0.0" />
    <detection t="240" x="331.18272166751615" y="294.3109007107692" z="0.0" />
    <detection t="241" x="330.87494185993154" y="294.3901063625192" z="0.0" />
    <detection t="242" x="330.42287481067166" y="293.4996054667728" z="0.0" />
    <detection t="243" x="331.3580892335571" y="294.76359146085514" z="0.0" />
    <detection t="244" x="331.1774449918313" y="294.2606717102904" z="0.0" />
    <detection t="245" x="331.23954378446854" y="294.74505385746744" z="0.0" />
    <detection t="246" x="331.45335529559776" y="294.6338428832947" z="0.0" />
    <detection t="247" x="330.7556488761395" y="295.2285983762822" z="0.0" />
    <detection t="248" x="331.45722144276345" y="294.4193071600083" z="0.0" />
    <detection t="249" x="330.8800541637006" y="294.5685922026572" z="0.0" />
    <detection t="250" x="330.96645993938307" y="294.86339405736356" z="0.0" />
    <detection t="251" x="330.7023593130657" y="294.23585574815365" z="0.0" />
    <detection t="252" x="330.91249251962205" y="294.27689255789835" z="0.0" />
    <detection t="253" x="330.63463313372256" y="294.2791616363749" z="0.0" />
    <detection t="254" x="330.9096037811538" y="293.8804688890625" z="0.0" />
    <detection t="255" x="330.92853639814126" y="294.17872908086974" z="0.0" />
    <detection t="256" x="331.36513341786025" y="294.9722424736361" z="0.0" />
    <detection t="257" x="332.4542638862873" y="295.03378038281" z="0.0" />
    <detection t="258" x="331.07716676529964" y="294.8321230964005" z="0.0" />
    <detection t="259" x="330.6328347184574" y="294.3028837752789" z="0.0" />
    <detection t="260" x="330.72809443367777" y="295.0024319239815" z="0.0" />
    <detection t="261" x="331.18310356807405" y="295.03696226885256" z="0.0" />
    <detection t="262" x="330.8845551822527" y="295.0696267757837" z="0.0" />
    <detection t="263" x="330.3595485499078" y="294.3559905675974" z="0.0" />
    <detection t="264" x="330.14604441627927" y="295.8837566911499" z="0.0" />
    <detection t="265" x="329.5027884968887" y="295.3313296960592" z="0.0" />
    <detection t="266" x="329.21863823206064" y="294.49710502635037" z="0.0" />
    <detection t="267" x="329.69672006072403" y="294.80850275417913" z="0.0" />
    <detection t="268" x="330.5950237600276" y="295.10804693692046" z="0.0" />
    <detection t="269" x="330.4368532560048" y="294.4278263619483" z="0.0" />
    <detection t="270" x="330.61351329587154" y="294.9918672083279" z="0.0" />
    <detection t="271" x="330.9408930721487" y="294.8650683255935" z="0.0" />
    <detection t="272" x="330.1283316049392" y="295.0253338009552" z="0.0" />
    <detection t="273" x="330.3421451221298" y="295.0444422901578" z="0.0" />
    <detection t="274" x="330.8189480585367" y="294.7916762233276" z="0.0" />
    <detection t="275" x="330.7792181131543" y="294.7135124878936" z="0.0" />
    <detection t="276" x="330.7117964451764" y="293.86835821995544" z="0.0" />
    <detection t="277" x="330.33669256239614" y="294.1373467810649" z="0.0" />
    <detection t="278" x="331.14685726940013" y="293.7770855740441" z="0.0" />
    <detection t="279" x="330.81454192588603" y="293.83161733564356" z="0.0" />
    <detection t="280" x="330.7444051457378" y="293.9792662578861" z="0.0" />
    <detection t="281" x="330.35496468793605" y="293.6874723881978" z="0.0" />
    <detection t="282" x="330.53238486434793" y="293.72664044923897" z="0.0" />
    <detection t="283" x="330.6667136897747" y="293.7379029492266" z="0.0" />
    <detection t="284" x="330.50155549325467" y="293.8676289837851" z="0.0" />
    <detection t="285" x="331.00192487129135" y="293.5485225755227" z="0.0" />
    <detection t="286" x="331.21389592588287" y="293.5309537168133" z="0.0" />
    <detection t="287" x="330.2977222341495" y="293.7763879476811" z="0.0" />
    <detection t="288" x="329.69416046611383" y="294.0588924242278" z="0.0" />
    <detection t="289" x="330.1480175402135" y="294.16482882131686" z="0.0" />
    <detection t="290" x="330.01045514198347" y="294.55228482903755" z="0.0" />
    <detection t="291" x="330.6648333432657" y="294.58121551303975" z="0.0" />
    <detection t="292" x="329.76367166350644" y="293.6015386906893" z="0.0" />
    <detection t="293" x="329.66844801007016" y="293.5835924513972" z="0.0" />
    <detection t="294" x="330.41010283514123" y="293.87747448009844" z="0.0" />
    <detection t="295" x="331.0551912981111" y="293.83026218459605" z="0.0" />
    <detection t="296" x="330.215239079699" y="293.30120815945133" z="0.0" />
    <detection t="297" x="330.76272079442873" y="293.5951163151977" z="0.0" />
    <detection t="298" x="330.8804570461334" y="293.7715796505306" z="0.0" />
    <detection t="299" x="330.2483207049047" y="293.7145688091573" z="0.0" />
    <detection t="300" x="330.1312039599177" y="293.98525402843507" z="0.0" />
    <detection t="301" x="329.8980975312614" y="294.0379284712232" z="0.0" />
    <detection t="302" x="330.66032403380234" y="293.3175716392741" z="0.0" />
    <detection t="303" x="330.6093891659268" y="293.6344671951626" z="0.0" />
    <detection t="304" x="330.02083536712314" y="294.2389440731153" z="0.0" />
    <detection t="305" x="330.7375340382079" y="294.272733780145" z="0.0" />
    <detection t="306" x="330.00197041665666" y="294.38213756532537" z="0.0" />
    <detection t="307" x="330.0605734532295" y="294.4806295445073" z="0.0" />
    <detection t="308" x="330.1927433883075" y="294.0607683803925" z="0.0" />
    <detection t="309" x="330.08797736114894" y="292.8511207075055" z="0.0" />
    <detection t="310" x="329.81861611410733" y="293.85679836717804" z="0.0" />
    <detection t="311" x="330.06741186549897" y="293.18212087326265" z="0.0" />
    <detection t="312" x="331.0299384825143" y="293.5602582900544" z="0.0" />
    <detection t="313" x="329.4416854289296" y="294.049995203774" z="0.0" />
    <detection t="314" x="329.8136011512481" y="293.4405354922893" z="0.0" />
    <detection t="315" x="329.8272070162618" y="293.9972066060489" z="0.0" />
    <detection t="316" x="329.8509853919812" y="294.08567292677697" z="0.0" />
    <detection t="317" x="329.4125947460042" y="294.21815484971194" z="0.0" />
    <detection t="318" x="330.1067791983464" y="293.39773328467993" z="0.0" />
    <detection t="319" x="330.1274652617395" y="293.92995772070066" z="0.0" />
    <detection t="320" x="330.09451500697276" y="293.01677565641586" z="0.0" />
    <detection t="321" x="330.11942748186584" y="293.02675242205055" z="0.0" />
    <detection t="322" x="330.6709089545522" y="293.05135699800513" z="0.0" />
    <detection t="323" x="329.8989644898673" y="293.54664470658975" z="0.0" />
    <detection t="324" x="330.2338653726901" y="294.46894027361367" z="0.0" />
    <detection t="325" x="330.18345278992035" y="294.1127010155232" z="0.0" />
    <detection t="326" x="330.12165092193146" y="294.10228917967004" z="0.0" />
    <detection t="327" x="330.8870060991403" y="294.0872667702886" z="0.0" />
    <detection t="328" x="329.67995202665946" y="293.92910842366877" z="0.0" />
    <detection t="329" x="330.2220392226133" y="293.81517984724184" z="0.0" />
    <detection t="330" x="329.6643239510368" y="294.65495824258477" z="0.0" />
    <detection t="331" x="331.16875542706225" y="295.0307531543378" z="0.0" />
    <detection t="332" x="331.2042278566679" y="294.05398674400885" z="0.0" />
    <detection t="333" x="329.6043002539982" y="293.5017688820271" z="0.0" />
    <detection t="334" x="329.6689050489494" y="293.5513723949373" z="0.0" />
    <detection t="335" x="330.53108669026045" y="293.738548469483" z="0.0" />
    <detection t="336" x="329.9248452723045" y="294.05908011834396" z="0.0" />
    <detection t="337" x="329.9254924703404" y="294.29498701502604" z="0.0" />
    <detection t="338" x="329.4042883048488" y="293.99881282636045" z="0.0" />
    <detection t="339" x="329.3882506753746" y="293.83464955872216" z="0.0" />
    <detection t="340" x="329.9316451698575" y="294.04438053024325" z="0.0" />
    <detection t="341" x="329.96403855752743" y="294.75452201978504" z="0.0" />
    <detection t="342" x="330.0300342685671" y="292.9953882015813" z="0.0" />
    <detection t="343" x="330.6251602834465" y="293.4354662921704" z="0.0" />
    <detection t="344" x="329.95811326889765" y="293.40264280467545" z="0.0" />
    <detection t="345" x="329.55850582748246" y="293.75823876825984" z="0.0" />
    <detection t="346" x="330.88150675157493" y="293.46915707098793" z="0.0" />
    <detection t="347" x="329.82276025462414" y="293.168454566444" z="0.0" />
    <detection t="348" x="329.7238697619862" y="293.41017865283925" z="0.0" />
    <detection t="349" x="330.00767581712995" y="293.6363181135069" z="0.0" />
    <detection t="350" x="329.8296932520482" y="293.90796490636836" z="0.0" />
    <detection t="351" x="330.7599336207209" y="293.8011038936936" z="0.0" />
    <detection t="352" x="329.86307723861336" y="292.890311511269" z="0.0" />
    <detection t="353" x="329.9726314295099" y="293.63311612908143" z="0.0" />
    <detection t="354" x="330.0197998361375" y="293.354058194242" z="0.0" />
    <detection t="355" x="329.8620998706707" y="293.66515856145566" z="0.0" />
    <detection t="356" x="330.01314748401927" y="294.02013223823235" z="0.0" />
    <detection t="357" x="329.5163557698981" y="293.6130915093625" z="0.0" />
    <detection t="358" x="330.0966570616236" y="293.7753018337778" z="0.0" />
    <detection t="359" x="329.84448995668504" y="293.96529391042014" z="0.0" />
    <detection t="360" x="329.8223896405194" y="293.622726900951" z="0.0" />
    <detection t="361" x="331.2115605788232" y="293.71134076428905" z="0.0" />
    <detection t="362" x="330.90524625475945" y="294.27040777359076" z="0.0" />
    <detection t="363" x="330.99762539976115" y="293.28584287683606" z="0.0" />
    <detection t="364" x="330.7335552597116" y="293.46663513304577" z="0.0" />
    <detection t="365" x="330.97196374987135" y="294.52563667580756" z="0.0" />
    <detection t="366" x="330.30053473186484" y="294.01659962850994" z="0.0" />
    <detection t="367" x="329.39572609877524" y="293.4256041481334" z="0.0" />
    <detection t="368" x="329.4725167384319" y="294.2103652976043" z="0.0" />
    <detection t="369" x="329.3938700977398" y="293.41948584852304" z="0.0" />
    <detection t="370" x="330.74194405692805" y="292.7639041375532" z="0.0" />
    <detection t="371" x="330.1519451247849" y="293.02566418097484" z="0.0" />
    <detection t="372" x="330.1420223607" y="294.6006406405181" z="0.0" />
    <detection t="373" x="329.39345426701584" y="293.66608473238693" z="0.0" />
    <detection t="374" x="329.2614606033039" y="293.16431083295" z="0.0" />
    <detection t="375" x="330.4974767204401" y="293.9376137712074" z="0.0" />
    <detection t="376" x="330.44466580796075" y="294.1949816978657" z="0.0" />
    <detection t="377" x="329.614384123786" y="293.706742768052" z="0.0" />
    <detection t="378" x="329.7079206607782" y="293.48883316389083" z="0.0" />
    <detection t="379" x="330.3178392387669" y="294.70006994537766" z="0.0" />
    <detection t="380" x="329.41256898960677" y="294.19030633336035" z="0.0" />
    <detection t="381" x="329.3703046776874" y="294.3180713910719" z="0.0" />
    <detection t="382" x="329.0558314976758" y="294.2635025711789" z="0.0" />
    <detection t="383" x="329.4395304878085" y="293.59274385875705" z="0.0" />
    <detection t="384" x="328.12333353599996" y="292.3898240483496" z="0.0" />
    <detection t="385" x="328.14644991843744" y="293.1065078435193" z="0.0" />
    <detection t="386" x="329.1621180284139" y="293.538087560198" z="0.0" />
    <detection t="387" x="329.37388081476337" y="292.63632385788446" z="0.0" />
    <detection t="388" x="328.8480019463008" y="293.15185674290944" z="0.0" />
    <detection t="389" x="329.48861139785686" y="293.3861029158424" z="0.0" />
    <detection t="390" x="329.95207691375987" y="292.9689181529741" z="0.0" />
    <detection t="391" x="330.51810184388484" y="293.7023831239633" z="0.0" />
    <detection t="392" x="329.4898284391752" y="292.8228343346662" z="0.0" />
    <detection t="393" x="329.6615261499283" y="292.7467483161764" z="0.0" />
    <detection t="394" x="330.19302843361555" y="293.0129393166074" z="0.0" />
    <detection t="396" x="329.8301007493761" y="293.0273667393485" z="0.0" />
    <detection t="397" x="329.9049122804947" y="293.06291986087" z="0.0" />
    <detection t="398" x="330.68654065323045" y="293.7108881338664" z="0.0" />
    <detection t="399" x="330.91109480587903" y="292.98431879695636" z="0.0" />
    <detection t="401" x="330.9587429834564" y="293.12759669455505" z="0.0" />
    <detection t="402" x="329.7379936637052" y="292.51107935930264" z="0.0" />
    <detection t="403" x="329.503227547179" y="293.4853188713861" z="0.0" />
    <detection t="404" x="329.56702257826413" y="293.02624726692727" z="0.0" />
    <detection t="405" x="329.57865105929017" y="293.71258154797005" z="0.0" />
    <detection t="406" x="328.53861862263494" y="294.34195968536994" z="0.0" />
    <detection t="407" x="328.1316046295159" y="294.16779329666997" z="0.0" />
    <detection t="408" x="328.66171228732406" y="293.940521499629" z="0.0" />
    <detection t="409" x="329.7116061947162" y="293.5222168720607" z="0.0" />
    <detection t="410" x="329.71347823587274" y="293.9512020056395" z="0.0" />
    <detection t="411" x="331.82632718183146" y="294.21822262049176" z="0.0" />
    <detection t="412" x="330.25672388642187" y="293.04057540430074" z="0.0" />
    <detection t="413" x="329.30923822592365" y="293.14751462608194" z="0.0" />
    <detection t="414" x="330.248941824258" y="293.9155219465057" z="0.0" />
    <detection t="415" x="329.7803264505048" y="293.6331928712564" z="0.0" />
    <detection t="416" x="332.58467592623003" y="292.8977468573106" z="0.0" />
    <detection t="417" x="329.9104797433682" y="293.3461142652438" z="0.0" />
    <detection t="418" x="330.6520596467347" y="292.71017867783513" z="0.0" />
    <detection t="419" x="330.1267504970498" y="292.6342630165929" z="0.0" />
    <detection t="420" x="330.7033452997498" y="293.9587912700246" z="0.0" />
    <detection t="421" x="329.34498770434436" y="292.8152250325572" z="0.0" />
    <detection t="422" x="330.2556917735498" y="293.0601615469877" z="0.0" />
    <detection t="423" x="330.39743076834634" y="292.5664969792707" z="0.0" />
    <detection t="424" x="329.7939549927229" y="291.9474156665025" z="0.0" />
    <detection t="425" x="329.7788154150621" y="292.8104335241847" z="0.0" />
    <detection t="426" x="329.9760876518241" y="291.9961016680048" z="0.0" />
    <detection t="427" x="330.11012961425234" y="292.6833486591177" z="0.0" />
    <detection t="428" x="330.3566756744161" y="291.96230983083564" z="0.0" />
    <detection t="429" x="329.79082992822214" y="292.7570275358216" z="0.0" />
    <detection t="430" x="330.9413488548124" y="292.978934040162" z="0.0" />
    <detection t="431" x="330.33414622800456" y="293.0351490198095" z="0.0" />
    <detection t="432" x="330.76157509677097" y="292.75524170085737" z="0.0" />
    <detection t="433" x="331.0436202261859" y="292.1326147106783" z="0.0" />
    <detection t="434" x="331.0885505234425" y="292.771063744533" z="0.0" />
    <detection t="435" x="331.1243793183354" y="293.18374275177746" z="0.0" />
    <detection t="436" x="331.2776001504953" y="292.9301592069055" z="0.0" />
    <detection t="437" x="332.15179702186174" y="292.3001459322264" z="0.0" />
    <detection t="438" x="331.73227134131474" y="293.2317930325856" z="0.0" />
    <detection t="439" x="331.184582851532" y="292.89676424420634" z="0.0" />
    <detection t="440" x="331.51673226858026" y="293.4919562099163" z="0.0" />
    <detection t="441" x="330.5162246161619" y="292.7493186386558" z="0.0" />
    <detection t="442" x="330.48646806565176" y="293.23079084302987" z="0.0" />
    <detection t="443" x="329.6226128034578" y="293.7817981218856" z="0.0" />
    <detection t="444" x="331.1387525043215" y="293.66406932514565" z="0.0" />
    <detection t="445" x="330.1772335264039" y="292.9786689461738" z="0.0" />
    <detection t="446" x="328.9958875063312" y="293.6843895544384" z="0.0" />
    <detection t="447" x="330.182659780431" y="292.63546079608835" z="0.0" />
    <detection t="448" x="330.4748894643142" y="292.54381173390897" z="0.0" />
    <detection t="449" x="330.9345551075492" y="291.07613887274397" z="0.0" />
    <detection t="450" x="331.03581928514325" y="292.7523203872014" z="0.0" />
    <detection t="452" x="330.81374172644604" y="292.3050737358247" z="0.0" />
    <detection t="453" x="330.3053257040317" y="293.23703452903317" z="0.0" />
    <detection t="454" x="330.6395765828002" y="292.5067297005671" z="0.0" />
    <detection t="455" x="331.26493397101007" y="292.3805313327631" z="0.0" />
    <detection t="456" x="331.72004157317616" y="292.99321514179474" z="0.0" />
    <detection t="457" x="331.6071476920538" y="293.47708795682973" z="0.0" />
    <detection t="458" x="331.48556602762926" y="292.96082428896807" z="0.0" />
    <detection t="459" x="332.162190127783" y="293.1134300295024" z="0.0" />
    <detection t="461" x="331.8346422244413" y="293.0317566201786" z="0.0" />
    <detection t="462" x="332.50928289817983" y="292.82975733081275" z="0.0" />
  </particle>
  <particle nSpots="118">
    <detection t="496" x="332.10855461957914" y="294.1888633725541" z="0.0" />
    <detection t="497" x="331.9156902468568" y="293.9585068006694" z="0.0" />
    <detection t="498" x="332.64788685554225" y="293.43995429675726" z="0.0" />
    <detection t="499" x="331.46598556006694" y="293.68643539989336" z="0.0" />
    <detection t="501" x="333.3560329825139" y="293.83073183706404" z="0.0" />
    <detection t="502" x="331.83864610468686" y="293.8154890779612" z="0.0" />
    <detection t="503" x="332.8593099876415" y="293.3395894129643" z="0.0" />
    <detection t="504" x="331.46107713722927" y="293.0896683050866" z="0.0" />
    <detection t="505" x="331.87574669635865" y="293.6704479177994" z="0.0" />
    <detection t="506" x="332.34075870782743" y="292.1307649202981" z="0.0" />
    <detection t="507" x="332.28434151948665" y="292.8904573942606" z="0.0" />
    <detection t="508" x="332.4967534966237" y="293.8214942520253" z="0.0" />
    <detection t="509" x="330.8308803292414" y="293.39015975711476" z="0.0" />
    <detection t="510" x="331.39275057437334" y="293.758333586002" z="0.0" />
    <detection t="511" x="332.7121241809842" y="292.25465798420197" z="0.0" />
    <detection t="512" x="332.5759658282919" y="292.2677830457695" z="0.0" />
    <detection t="515" x="331.12761239014094" y="292.08487657933335" z="0.0" />
    <detection t="516" x="331.9373446300182" y="293.314264475776" z="0.0" />
    <detection t="517" x="331.67245797421" y="293.69276997838597" z="0.0" />
    <detection t="518" x="332.15679689527093" y="293.7794498317063" z="0.0" />
    <detection t="519" x="332.0131359788393" y="293.427600257553" z="0.0" />
    <detection t="520" x="332.5065990803142" y="293.8752305114847" z="0.0" />
    <detection t="521" x="332.50234294885695" y="293.5642166255537" z="0.0" />
    <detection t="522" x="332.6953097889307" y="292.94006832891006" z="0.0" />
    <detection t="523" x="332.3546644535132" y="292.5482553526455" z="0.0" />
    <detection t="524" x="331.96398214054454" y="293.7370225950436" z="0.0" />
    <detection t="525" x="333.58516507243615" y="293.6769092817031" z="0.0" />
    <detection t="526" x="332.26759491400134" y="293.2683219148532" z="0.0" />
    <detection t="527" x="332.47332365585453" y="293.82666314398307" z="0.0" />
    <detection t="528" x="332.04993802181514" y="293.57213569684575" z="0.0" />
    <detection t="529" x="333.8203316516532" y="293.47978848944064" z="0.0" />
    <detection t="530" x="332.6604054368538" y="293.95255016350785" z="0.0" />
    <detection t="531" x="333.0985864199339" y="293.63456562510703" z="0.0" />
    <detection t="532" x="331.9915984521394" y="293.7234418108771" z="0.0" />
    <detection t="533" x="332.68918211790157" y="294.0039268849475" z="0.0" />
    <detection t="534" x="332.6502442713132" y="293.74705220378917" z="0.0" />
    <detection t="535" x="332.51105992244675" y="293.78189141241" z="0.0" />
    <detection t="536" x="332.523302722467" y="293.6187830851857" z="0.0" />
    <detection t="537" x="332.76896586643323" y="292.6754614107633" z="0.0" />
    <detection t="538" x="332.4207536028924" y="293.4347846041807" z="0.0" />
    <detection t="539" x="332.2339617395383" y="294.13139537155126" z="0.0" />
    <detection t="540" x="332.398702530901" y="294.0614640742306" z="0.0" />
    <detection t="541" x="332.36113425144293" y="293.9496006342724" z="0.0" />
    <detection t="542" x="331.74485364456854" y="294.0266334699096" z="0.0" />
    <detection t="543" x="331.9895541826149" y="293.597065231698" z="0.0" />
    <detection t="544" x="331.86343423137384" y="293.6977535419256" z="0.0" />
    <detection t="545" x="331.2829769708506" y="293.210892058469" z="0.0" />
    <detection t="546" x="331.49526735143024" y="294.34143566358586" z="0.0" />
    <detection t="547" x="332.2784079483947" y="294.19935391597926" z="0.0" />
    <detection t="548" x="331.37599635306555" y="293.8028800807087" z="0.0" />
    <detection t="549" x="332.2383698576047" y="294.25714828281536" z="0.0" />
    <detection t="550" x="332.76316983561355" y="294.15857149813206" z="0.0" />
    <detection t="551" x="332.1250014050166" y="294.2093632604835" z="0.0" />
    <detection t="552" x="331.4895947208251" y="294.36235789670053" z="0.0" />
    <detection t="553" x="331.4935225040431" y="293.7935447922323" z="0.0" />
    <detection t="554" x="332.95674623213813" y="293.617954070092" z="0.0" />
    <detection t="555" x="331.96597318744347" y="293.70488974273036" z="0.0" />
    <detection t="556" x="332.3542423468261" y="292.9373636009634" z="0.0" />
    <detection t="557" x="332.2694190292753" y="293.0688593996669" z="0.0" />
    <detection t="558" x="332.38985563668393" y="292.9349987621399" z="0.0" />
    <detection t="559" x="332.50588184260965" y="293.7755763228867" z="0.0" />
    <detection t="560" x="332.5539003427489" y="294.1159970709681" z="0.0" />
    <detection t="561" x="332.6452119029028" y="294.0807914810931" z="0.0" />
    <detection t="562" x="332.87954369553887" y="293.65152663893184" z="0.0" />
    <detection t="563" x="333.0020292269715" y="294.81667972466124" z="0.0" />
    <detection t="564" x="332.0838683349432" y="295.3578640739823" z="0.0" />
    <detection t="565" x="332.54884109814236" y="294.8498842215772" z="0.0" />
    <detection t="566" x="332.6881752917057" y="294.09300649664465" z="0.0" />
    <detection t="567" x="332.8197274150053" y="295.11039742279314" z="0.0" />
    <detection t="568" x="332.1579673466054" y="295.1041038316828" z="0.0" />
    <detection t="569" x="331.3017261187439" y="294.9202324969203" z="0.0" />
    <detection t="570" x="332.19531907628954" y="294.85544847533293" z="0.0" />
    <detection t="571" x="331.87219380011817" y="294.7674743794391" z="0.0" />
    <detection t="572" x="332.9782863170155" y="294.77962250074376" z="0.0" />
    <detection t="573" x="331.51485776074543" y="295.668335855113" z="0.0" />
    <detection t="574" x="332.23253791489475" y="294.97469091891116" z="0.0" />
    <detection t="575" x="333.22399088932013" y="294.7697909920427" z="0.0" />
    <detection t="576" x="332.26840950186397" y="293.6341105197601" z="0.0" />
    <detection t="577" x="333.1979179122563" y="294.8886639141498" z="0.0" />
    <detection t="578" x="331.9804526705001" y="294.8847977705925" z="0.0" />
    <detection t="579" x="332.8561916341759" y="293.6884501572883" z="0.0" />
    <detection t="580" x="332.4891837523577" y="293.48565854164826" z="0.0" />
    <detection t="581" x="332.5360171418196" y="293.60393636077356" z="0.0" />
    <detection t="582" x="332.65516915002087" y="293.9155205007367" z="0.0" />
    <detection t="583" x="332.9214776656726" y="293.6316051530276" z="0.0" />
    <detection t="584" x="333.74475301958154" y="293.8483870100378" z="0.0" />
    <detection t="585" x="333.162154121428" y="294.47181528493866" z="0.0" />
    <detection t="586" x="332.1069325041006" y="293.953094648141" z="0.0" />
    <detection t="587" x="333.0042327694069" y="293.78264855172046" z="0.0" />
    <detection t="588" x="333.07707166238094" y="293.95127544787766" z="0.0" />
    <detection t="589" x="333.53679534521535" y="294.0221609134333" z="0.0" />
    <detection t="590" x="332.73899916097037" y="292.7433066710916" z="0.0" />
    <detection t="591" x="333.06890129565465" y="293.17360273300187" z="0.0" />
    <detection t="592" x="332.85726572122167" y="293.3987435245355" z="0.0" />
    <detection t="593" x="333.5037508338534" y="294.4863702940748" z="0.0" />
    <detection t="594" x="334.4263869375876" y="295.0432660154281" z="0.0" />
    <detection t="595" x="333.1039432844533" y="294.92530270072905" z="0.0" />
    <detection t="596" x="332.98712625178246" y="293.82055654671615" z="0.0" />
    <detection t="597" x="333.12904766802467" y="294.7514563265164" z="0.0" />
    <detection t="599" x="333.8962127268224" y="294.702520434558" z="0.0" />
    <detection t="600" x="333.5056519400872" y="296.0254866270144" z="0.0" />
    <detection t="601" x="333.1329792012491" y="294.5731815279552" z="0.0" />
    <detection t="602" x="333.8008874180635" y="293.96859673392004" z="0.0" />
    <detection t="603" x="334.1941992034354" y="294.2264803748003" z="0.0" />
    <detection t="604" x="333.097489344853" y="293.57038438803437" z="0.0" />
    <detection t="605" x="333.30018611689934" y="293.50313023216165" z="0.0" />
    <detection t="606" x="333.3449961141552" y="294.1758366333779" z="0.0" />
    <detection t="607" x="334.0675522524825" y="293.9863580526331" z="0.0" />
    <detection t="608" x="333.3456561336734" y="294.3188064975831" z="0.0" />
    <detection t="609" x="333.8886992397121" y="294.2813618131116" z="0.0" />
    <detection t="610" x="332.4916211941526" y="294.73266104174485" z="0.0" />
    <detection t="611" x="333.307807143256" y="294.5712274702679" z="0.0" />
    <detection t="612" x="333.4864210418074" y="295.08386913047605" z="0.0" />
    <detection t="613" x="332.1498423191012" y="294.22961163363027" z="0.0" />
    <detection t="614" x="332.57611891813025" y="295.37603723717024" z="0.0" />
    <detection t="615" x="332.8961406165057" y="294.658063742452" z="0.0" />
    <detection t="616" x="332.3174272594684" y="294.4402675050025" z="0.0" />
    <detection t="617" x="332.6998941122363" y="293.8870764189084" z="0.0" />
  </particle>
  <particle nSpots="324">
    <detection t="673" x="334.845467288679" y="296.37807099688376" z="0.0" />
    <detection t="674" x="332.23565095308516" y="294.2228934158486" z="0.0" />
    <detection t="675" x="331.89749969933104" y="295.7931219539849" z="0.0" />
    <detection t="676" x="332.101129691543" y="294.79277714194507" z="0.0" />
    <detection t="677" x="332.14576693540675" y="295.9432360157955" z="0.0" />
    <detection t="678" x="334.6308141665054" y="295.30263100604196" z="0.0" />
    <detection t="679" x="332.09101005610836" y="294.3214974727345" z="0.0" />
    <detection t="680" x="333.06536625716484" y="294.2758616446428" z="0.0" />
    <detection t="681" x="334.0648996103998" y="295.14757703845703" z="0.0" />
    <detection t="682" x="333.05350715448276" y="294.8137408369091" z="0.0" />
    <detection t="684" x="332.88627725268145" y="293.36752758834285" z="0.0" />
    <detection t="685" x="333.2998882823793" y="294.35548144549676" z="0.0" />
    <detection t="686" x="332.96025841307585" y="293.9257723931796" z="0.0" />
    <detection t="687" x="333.0817945245364" y="293.91243108464164" z="0.0" />
    <detection t="688" x="333.73067726731944" y="293.8750445232702" z="0.0" />
    <detection t="689" x="333.3829372479217" y="293.8484457911308" z="0.0" />
    <detection t="690" x="334.0976903782548" y="293.5447170803476" z="0.0" />
    <detection t="691" x="334.4829819257518" y="293.1923828992789" z="0.0" />
    <detection t="692" x="333.61621418377155" y="293.01966435228076" z="0.0" />
    <detection t="693" x="333.98299441280056" y="293.3974311907502" z="0.0" />
    <detection t="694" x="335.0581118085731" y="293.9925378445456" z="0.0" />
    <detection t="695" x="334.2829194849507" y="294.41498178373485" z="0.0" />
    <detection t="696" x="334.01522753664807" y="293.9734796678861" z="0.0" />
    <detection t="697" x="334.08525743145617" y="294.0293026984425" z="0.0" />
    <detection t="698" x="334.8201914439375" y="293.8938515303177" z="0.0" />
    <detection t="699" x="333.7726393993479" y="293.9146943628098" z="0.0" />
    <detection t="700" x="334.8534353407818" y="293.52816755490556" z="0.0" />
    <detection t="701" x="333.7828601957519" y="294.17238563648664" z="0.0" />
    <detection t="702" x="333.7222822852855" y="294.3459274468857" z="0.0" />
    <detection t="703" x="333.8290070058075" y="294.4236265952731" z="0.0" />
    <detection t="704" x="334.4811612990497" y="294.29270356474404" z="0.0" />
    <detection t="705" x="334.63880694989257" y="293.6726446375205" z="0.0" />
    <detection t="706" x="334.4251445703225" y="294.1405893512529" z="0.0" />
    <detection t="707" x="333.69804119927437" y="294.1540536292804" z="0.0" />
    <detection t="708" x="334.3267993938008" y="294.524824874997" z="0.0" />
    <detection t="709" x="333.6691757512337" y="294.18892176405365" z="0.0" />
    <detection t="710" x="334.26246606405306" y="294.1154126676123" z="0.0" />
    <detection t="711" x="334.78345159420843" y="294.5928300130341" z="0.0" />
    <detection t="712" x="333.9235611882293" y="295.06995110778837" z="0.0" />
    <detection t="713" x="333.5019302622595" y="294.0253240368946" z="0.0" />
    <detection t="714" x="332.95861315287476" y="294.33971241632565" z="0.0" />
    <detection t="715" x="333.82026401667684" y="293.7881543823362" z="0.0" />
    <detection t="716" x="333.3555341658807" y="293.99783683904036" z="0.0" />
    <detection t="717" x="333.275563675423" y="295.0500534538681" z="0.0" />
    <detection t="718" x="332.725504614172" y="294.73931580438114" z="0.0" />
    <detection t="719" x="333.4353715959058" y="294.86755650295464" z="0.0" />
    <detection t="720" x="332.8212688860828" y="295.14948197171407" z="0.0" />
    <detection t="721" x="333.20542101339225" y="294.75991898276163" z="0.0" />
    <detection t="722" x="334.117926572312" y="294.66885143881353" z="0.0" />
    <detection t="723" x="333.91019462354825" y="294.3305970002959" z="0.0" />
    <detection t="724" x="333.5701651714726" y="294.10646799402826" z="0.0" />
    <detection t="725" x="333.692481479793" y="293.83464557336515" z="0.0" />
    <detection t="726" x="333.7103017185591" y="293.98801144604704" z="0.0" />
    <detection t="727" x="333.8766414708701" y="294.3226415405815" z="0.0" />
    <detection t="728" x="334.9627091654042" y="294.0540991508029" z="0.0" />
    <detection t="729" x="334.33687094187525" y="294.6304435121401" z="0.0" />
    <detection t="730" x="333.25057677675045" y="294.10826982926596" z="0.0" />
    <detection t="731" x="333.9519647102596" y="293.8719231885592" z="0.0" />
    <detection t="732" x="334.46280881461024" y="294.3462959762937" z="0.0" />
    <detection t="733" x="333.7715064402944" y="294.67274213827585" z="0.0" />
    <detection t="734" x="333.90145830420533" y="294.0903163904441" z="0.0" />
    <detection t="735" x="333.60059129835054" y="293.7822183950529" z="0.0" />
    <detection t="736" x="334.1863805798461" y="294.2078534706813" z="0.0" />
    <detection t="737" x="333.47463896463233" y="294.48790627920414" z="0.0" />
    <detection t="738" x="333.1353619016168" y="294.0642535910855" z="0.0" />
    <detection t="739" x="334.40290576497245" y="294.71053486990655" z="0.0" />
    <detection t="740" x="334.304859214519" y="293.6451862033268" z="0.0" />
    <detection t="741" x="333.7769328455421" y="293.9159812097432" z="0.0" />
    <detection t="742" x="333.1473417298296" y="293.9290356754096" z="0.0" />
    <detection t="743" x="334.32330351621863" y="293.69129673543995" z="0.0" />
    <detection t="744" x="333.27172603072086" y="294.1306599423896" z="0.0" />
    <detection t="745" x="333.6857566451664" y="294.01884654133625" z="0.0" />
    <detection t="746" x="334.1877854057828" y="293.75248391357286" z="0.0" />
    <detection t="747" x="333.02077162465855" y="294.3292346698035" z="0.0" />
    <detection t="748" x="333.15922258024375" y="294.40697089170556" z="0.0" />
    <detection t="749" x="332.92129494328253" y="293.9188646984674" z="0.0" />
    <detection t="750" x="332.51788393283834" y="293.8697839896245" z="0.0" />
    <detection t="751" x="332.28616307739986" y="293.30156476184357" z="0.0" />
    <detection t="752" x="332.00221966650435" y="293.30496572660786" z="0.0" />
    <detection t="753" x="332.57315892104657" y="293.0713736767636" z="0.0" />
    <detection t="754" x="332.26291407259805" y="293.250771210126" z="0.0" />
    <detection t="755" x="332.90781680919525" y="292.7159338256739" z="0.0" />
    <detection t="756" x="332.4079623154143" y="293.10017632192324" z="0.0" />
    <detection t="757" x="332.27029389235327" y="293.09860593404267" z="0.0" />
    <detection t="758" x="331.4297663850054" y="292.8935646894408" z="0.0" />
    <detection t="759" x="332.6239296350047" y="293.1231790126317" z="0.0" />
    <detection t="760" x="332.62554458453246" y="293.8107639116009" z="0.0" />
    <detection t="761" x="332.7930673705134" y="293.62592164277487" z="0.0" />
    <detection t="762" x="332.5981431846967" y="294.32269673249016" z="0.0" />
    <detection t="763" x="333.4216356700192" y="293.7326823718595" z="0.0" />
    <detection t="764" x="334.00074533295896" y="294.2217394641945" z="0.0" />
    <detection t="765" x="334.32825468685195" y="293.6624778303114" z="0.0" />
    <detection t="766" x="334.9283338631156" y="293.45647937900833" z="0.0" />
    <detection t="767" x="334.4352142713076" y="293.93781095537435" z="0.0" />
    <detection t="768" x="334.4262693563557" y="293.6982831247501" z="0.0" />
    <detection t="769" x="334.3296368251978" y="293.7216841712723" z="0.0" />
    <detection t="770" x="334.0999809544138" y="294.0353501897975" z="0.0" />
    <detection t="771" x="334.0110684866225" y="294.1651317354875" z="0.0" />
    <detection t="772" x="333.92802085347597" y="293.7305139993863" z="0.0" />
    <detection t="773" x="333.6671892893562" y="292.14477229128477" z="0.0" />
    <detection t="774" x="333.86661355973723" y="293.9239455707004" z="0.0" />
    <detection t="775" x="333.8746577852017" y="293.67135599638715" z="0.0" />
    <detection t="776" x="333.04396877076607" y="293.75237914806917" z="0.0" />
    <detection t="777" x="334.15300560652713" y="294.1371096027781" z="0.0" />
    <detection t="778" x="333.43452029131953" y="293.3626147770595" z="0.0" />
    <detection t="779" x="334.4189352377134" y="292.7578595467749" z="0.0" />
    <detection t="780" x="333.1408196258107" y="292.8637567471776" z="0.0" />
    <detection t="781" x="333.1616286069943" y="293.1857730519072" z="0.0" />
    <detection t="782" x="333.66640284743715" y="293.539983728125" z="0.0" />
    <detection t="783" x="333.397716200906" y="293.37289055850687" z="0.0" />
    <detection t="784" x="333.08029180251464" y="293.3440035744567" z="0.0" />
    <detection t="785" x="333.76567427185296" y="292.95834209222215" z="0.0" />
    <detection t="786" x="333.2467761890463" y="293.4904641693967" z="0.0" />
    <detection t="787" x="333.45126440605367" y="293.17646419362165" z="0.0" />
    <detection t="788" x="332.98814901374004" y="293.2271195674033" z="0.0" />
    <detection t="789" x="333.50050207386806" y="292.7008646833211" z="0.0" />
    <detection t="790" x="332.7207207489201" y="292.57650116757605" z="0.0" />
    <detection t="791" x="333.2093995578133" y="292.36858340758664" z="0.0" />
    <detection t="792" x="333.06321446289445" y="293.04233183995166" z="0.0" />
    <detection t="793" x="333.7752375940057" y="293.00402360202935" z="0.0" />
    <detection t="794" x="333.4477513088522" y="291.93012496642933" z="0.0" />
    <detection t="795" x="333.9599879646171" y="292.13498236211115" z="0.0" />
    <detection t="796" x="334.5017396054928" y="292.28254102490047" z="0.0" />
    <detection t="797" x="334.09975776776565" y="292.65893597867444" z="0.0" />
    <detection t="798" x="334.0787471285805" y="292.5490510849242" z="0.0" />
    <detection t="799" x="334.53973004107587" y="292.7781433197483" z="0.0" />
    <detection t="800" x="333.9856436418119" y="293.02591218165065" z="0.0" />
    <detection t="801" x="334.1945684460636" y="293.40726842227116" z="0.0" />
    <detection t="802" x="334.0173321999301" y="292.99892046705077" z="0.0" />
    <detection t="803" x="334.51650802511637" y="293.2040811872719" z="0.0" />
    <detection t="804" x="334.5690035917652" y="292.65143107329413" z="0.0" />
    <detection t="805" x="334.7594563034387" y="293.2105826221272" z="0.0" />
    <detection t="806" x="335.48375179335966" y="292.4752870206883" z="0.0" />
    <detection t="807" x="334.82087841821146" y="292.68684587887844" z="0.0" />
    <detection t="808" x="335.642641151789" y="293.32880723093234" z="0.0" />
    <detection t="809" x="335.469869857556" y="293.48951994041096" z="0.0" />
    <detection t="810" x="335.0552784008844" y="293.41675343023746" z="0.0" />
    <detection t="811" x="335.43473066843734" y="293.6333715450186" z="0.0" />
    <detection t="812" x="334.27003496928046" y="294.25531602927697" z="0.0" />
    <detection t="813" x="334.89742203919724" y="293.4337416080304" z="0.0" />
    <detection t="814" x="334.9063227533182" y="293.4840967683552" z="0.0" />
    <detection t="815" x="335.755605619965" y="293.2516019609296" z="0.0" />
    <detection t="816" x="335.1846722506748" y="293.57740103401227" z="0.0" />
    <detection t="817" x="335.16173096502354" y="293.7749223353353" z="0.0" />
    <detection t="818" x="334.8030275445588" y="293.5453252394428" z="0.0" />
    <detection t="819" x="335.15413144164023" y="293.14985866067605" z="0.0" />
    <detection t="820" x="334.7479538229971" y="293.2150778381384" z="0.0" />
    <detection t="821" x="335.5325558271286" y="293.14346219677736" z="0.0" />
    <detection t="822" x="334.99287088350013" y="293.1638757903028" z="0.0" />
    <detection t="823" x="334.4004232502424" y="293.00508041462916" z="0.0" />
    <detection t="824" x="334.377115312626" y="293.49197836538804" z="0.0" />
    <detection t="825" x="333.7830737783929" y="292.6810555468457" z="0.0" />
    <detection t="826" x="334.24090206886274" y="293.4811694130179" z="0.0" />
    <detection t="827" x="334.37964782806256" y="292.74230836092875" z="0.0" />
    <detection t="828" x="335.2981252949596" y="293.21437563212146" z="0.0" />
    <detection t="829" x="334.61114475069263" y="293.19422104768563" z="0.0" />
    <detection t="830" x="335.0591540445858" y="293.60744436612856" z="0.0" />
    <detection t="831" x="333.9387593709382" y="293.3606785850699" z="0.0" />
    <detection t="832" x="334.6170302229185" y="294.10813207450246" z="0.0" />
    <detection t="833" x="334.27832274745964" y="293.121088368489" z="0.0" />
    <detection t="834" x="334.4535038566656" y="293.734209999844" z="0.0" />
    <detection t="835" x="333.9325750426015" y="293.89367384379335" z="0.0" />
    <detection t="836" x="333.88296709176507" y="294.11376386345245" z="0.0" />
    <detection t="837" x="334.5841844855586" y="294.14005193002527" z="0.0" />
    <detection t="838" x="335.0781495791072" y="293.923838841543" z="0.0" />
    <detection t="839" x="334.92989462241826" y="293.63091424846715" z="0.0" />
    <detection t="840" x="334.60378799996704" y="292.88504268236125" z="0.0" />
    <detection t="841" x="334.9877108577004" y="293.4489128318483" z="0.0" />
    <detection t="842" x="334.96508054701746" y="293.24142268796385" z="0.0" />
    <detection t="843" x="335.20556447672914" y="293.3992063118762" z="0.0" />
    <detection t="844" x="334.883204037952" y="293.8381766719896" z="0.0" />
    <detection t="845" x="335.4373159604087" y="293.65721062283023" z="0.0" />
    <detection t="846" x="335.19409121290994" y="293.7625381736485" z="0.0" />
    <detection t="847" x="335.0006614274706" y="293.7783156738799" z="0.0" />
    <detection t="848" x="334.7466184289946" y="293.58632783132197" z="0.0" />
    <detection t="849" x="334.96273569244903" y="293.159641498308" z="0.0" />
    <detection t="850" x="334.8370998783575" y="293.60632654279243" z="0.0" />
    <detection t="851" x="334.8796872148643" y="292.9270893775617" z="0.0" />
    <detection t="852" x="334.4078747421422" y="293.6084819979834" z="0.0" />
    <detection t="853" x="333.88880124384525" y="293.1235668007278" z="0.0" />
    <detection t="854" x="334.1791053547312" y="293.0559529823105" z="0.0" />
    <detection t="855" x="334.66243440318203" y="293.3176262128402" z="0.0" />
    <detection t="856" x="333.9695133069145" y="293.2109400461555" z="0.0" />
    <detection t="857" x="334.44293803722314" y="293.1686967023822" z="0.0" />
    <detection t="858" x="334.6258676695485" y="293.1860538221063" z="0.0" />
    <detection t="859" x="334.56959534876904" y="293.14894840386467" z="0.0" />
    <detection t="860" x="334.8269748503833" y="292.4157853360617" z="0.0" />
    <detection t="861" x="334.97319410527103" y="292.62569150416704" z="0.0" />
    <detection t="862" x="334.31268251399183" y="292.8278566776805" z="0.0" />
    <detection t="863" x="334.33661542376973" y="292.35987116717064" z="0.0" />
    <detection t="864" x="334.53749541399986" y="292.7108410823026" z="0.0" />
    <detection t="865" x="334.9039595574002" y="292.90592424879475" z="0.0" />
    <detection t="866" x="334.2531465111506" y="293.46808146987985" z="0.0" />
    <detection t="867" x="334.4219676262501" y="293.0365612445001" z="0.0" />
    <detection t="868" x="334.3707285333941" y="293.3309134759629" z="0.0" />
    <detection t="869" x="334.86594947609046" y="293.0315881465821" z="0.0" />
    <detection t="870" x="335.131719583083" y="292.56854651693345" z="0.0" />
    <detection t="871" x="333.812779374108" y="293.226846027761" z="0.0" />
    <detection t="872" x="334.24704017870107" y="293.0924776662832" z="0.0" />
    <detection t="873" x="334.6065582835929" y="293.19327477437787" z="0.0" />
    <detection t="874" x="333.6816434332299" y="293.79988167822734" z="0.0" />
    <detection t="875" x="334.0022992305077" y="293.53792218007766" z="0.0" />
    <detection t="876" x="333.7821141918047" y="293.0433909278177" z="0.0" />
    <detection t="877" x="335.20837089940244" y="293.07437693933764" z="0.0" />
    <detection t="878" x="335.2385602494665" y="293.099245101277" z="0.0" />
    <detection t="879" x="335.06313096334065" y="292.22669335936695" z="0.0" />
    <detection t="880" x="335.137178005789" y="293.5040213068718" z="0.0" />
    <detection t="881" x="334.8630902942654" y="293.388943129974" z="0.0" />
    <detection t="882" x="334.85581272311873" y="293.8525316112359" z="0.0" />
    <detection t="883" x="334.4684092272203" y="293.9578436044466" z="0.0" />
    <detection t="884" x="335.010085343788" y="294.2997995229065" z="0.0" />
    <detection t="885" x="335.37754747118345" y="293.99886199025553" z="0.0" />
    <detection t="886" x="334.9082187465709" y="294.2788737036176" z="0.0" />
    <detection t="887" x="335.0948285824092" y="294.35724171884186" z="0.0" />
    <detection t="888" x="335.1836932569566" y="293.84161633603816" z="0.0" />
    <detection t="889" x="335.5926378154023" y="294.00290519921265" z="0.0" />
    <detection t="890" x="335.4590223754861" y="294.8773146280868" z="0.0" />
    <detection t="891" x="335.95165622435945" y="294.3464233166595" z="0.0" />
    <detection t="892" x="335.7187568328801" y="294.2170386113184" z="0.0" />
    <detection t="893" x="335.2995655136736" y="294.44394647842387" z="0.0" />
    <detection t="894" x="335.9965513584994" y="294.20644271640737" z="0.0" />
    <detection t="895" x="335.5282393556419" y="294.3184127376614" z="0.0" />
    <detection t="896" x="335.4994522944463" y="293.2661971213456" z="0.0" />
    <detection t="897" x="335.1168717139187" y="293.81760773480624" z="0.0" />
    <detection t="898" x="335.1982292413478" y="294.564424986969" z="0.0" />
    <detection t="899" x="334.8252788864085" y="294.2428460934505" z="0.0" />
    <detection t="900" x="335.3165504898964" y="294.27126860436357" z="0.0" />
    <detection t="901" x="335.8933518063893" y="295.09649957539636" z="0.0" />
    <detection t="902" x="334.33690892981264" y="293.9530901283299" z="0.0" />
    <detection t="903" x="334.8924024368654" y="294.5328031034143" z="0.0" />
    <detection t="904" x="334.57260794984984" y="294.4376537838857" z="0.0" />
    <detection t="905" x="334.88637330014444" y="294.09170269303394" z="0.0" />
    <detection t="906" x="334.33824261850856" y="293.813328595841" z="0.0" />
    <detection t="907" x="335.42323474261224" y="294.1490446044104" z="0.0" />
    <detection t="908" x="335.2169817486667" y="293.6846368155626" z="0.0" />
    <detection t="909" x="335.16778834278244" y="293.7975562143552" z="0.0" />
    <detection t="910" x="334.3261818816373" y="293.64903700369587" z="0.0" />
    <detection t="911" x="334.36019670957296" y="294.3895360443855" z="0.0" />
    <detection t="912" x="335.17798701104135" y="294.00222760186244" z="0.0" />
    <detection t="913" x="335.7149887696824" y="293.6297094418709" z="0.0" />
    <detection t="914" x="335.1986975094155" y="294.05900035033284" z="0.0" />
    <detection t="915" x="335.68579790617054" y="293.944580139713" z="0.0" />
    <detection t="916" x="335.36946729884227" y="293.97307813205083" z="0.0" />
    <detection t="917" x="335.84900098453585" y="294.26355769723676" z="0.0" />
    <detection t="918" x="335.4793658149371" y="293.525579237528" z="0.0" />
    <detection t="919" x="335.6569699074304" y="294.3596730171577" z="0.0" />
    <detection t="920" x="334.58197324381644" y="294.22085550976374" z="0.0" />
    <detection t="921" x="336.00082585692775" y="293.79330294322864" z="0.0" />
    <detection t="922" x="335.51275337189514" y="293.8354612666398" z="0.0" />
    <detection t="923" x="336.2178826607587" y="293.2876413342818" z="0.0" />
    <detection t="924" x="336.06679539452176" y="293.78056480227605" z="0.0" />
    <detection t="925" x="335.48588703795497" y="294.15358103503354" z="0.0" />
    <detection t="926" x="336.2812258078092" y="294.2812488952322" z="0.0" />
    <detection t="927" x="334.51399366316537" y="294.6385551222993" z="0.0" />
    <detection t="928" x="333.892030215367" y="295.24517367542137" z="0.0" />
    <detection t="929" x="335.0270302033955" y="295.0688897542449" z="0.0" />
    <detection t="930" x="335.4387302221291" y="295.5484606701458" z="0.0" />
    <detection t="931" x="335.10989710371314" y="296.23071813981517" z="0.0" />
    <detection t="932" x="336.05024909409536" y="294.7584420873389" z="0.0" />
    <detection t="933" x="335.9569873190261" y="294.18563617871985" z="0.0" />
    <detection t="934" x="335.6907257335922" y="294.9674024506778" z="0.0" />
    <detection t="935" x="334.90986262981374" y="294.8803895844159" z="0.0" />
    <detection t="936" x="336.22237464047834" y="294.94453074217216" z="0.0" />
    <detection t="937" x="335.53784651605775" y="294.6322474788094" z="0.0" />
    <detection t="938" x="335.26352185328454" y="295.2721654276098" z="0.0" />
    <detection t="939" x="334.4525924222365" y="295.0818264119897" z="0.0" />
    <detection t="940" x="334.7570984729178" y="295.07794432251325" z="0.0" />
    <detection t="941" x="334.8234236030675" y="294.7629642236105" z="0.0" />
    <detection t="942" x="335.1748252856447" y="293.9531690640427" z="0.0" />
    <detection t="943" x="334.6814521350389" y="295.2609362633447" z="0.0" />
    <detection t="944" x="334.94375988402567" y="294.89348249217625" z="0.0" />
    <detection t="945" x="335.0812620669644" y="295.6385308540309" z="0.0" />
    <detection t="946" x="334.92795460659147" y="295.39759048629736" z="0.0" />
    <detection t="947" x="333.81086354668827" y="294.7608405317445" z="0.0" />
    <detection t="948" x="334.6589340301248" y="295.65603734543106" z="0.0" />
    <detection t="949" x="334.77920812833634" y="295.10606648198285" z="0.0" />
    <detection t="951" x="334.8282244033713" y="294.0223745187806" z="0.0" />
    <detection t="952" x="334.7320852034821" y="295.4694009501651" z="0.0" />
    <detection t="953" x="334.95960211264594" y="295.4536903752779" z="0.0" />
    <detection t="954" x="335.9953270667169" y="295.4303561908402" z="0.0" />
    <detection t="955" x="334.60609354957893" y="295.1210981146227" z="0.0" />
    <detection t="956" x="335.3267506779404" y="297.2268559328572" z="0.0" />
    <detection t="958" x="334.79236088610224" y="295.78921518853195" z="0.0" />
    <detection t="959" x="334.8528037615017" y="295.59480511054176" z="0.0" />
    <detection t="960" x="336.5344053126358" y="295.61870901730646" z="0.0" />
    <detection t="961" x="335.2633611691459" y="295.68680567930505" z="0.0" />
    <detection t="962" x="335.5594218520978" y="297.09207073107154" z="0.0" />
    <detection t="963" x="334.79702496469815" y="295.9031622359413" z="0.0" />
    <detection t="964" x="334.24716333338574" y="296.39304144050027" z="0.0" />
    <detection t="965" x="334.90992047545507" y="295.9993672472781" z="0.0" />
    <detection t="966" x="336.03474535913136" y="296.8470139408508" z="0.0" />
    <detection t="967" x="334.869731281376" y="296.3459770234233" z="0.0" />
    <detection t="968" x="335.0630955790444" y="295.18994588709137" z="0.0" />
    <detection t="969" x="334.41131561470405" y="296.1242888062619" z="0.0" />
    <detection t="970" x="334.4823259531907" y="296.46944250024546" z="0.0" />
    <detection t="971" x="334.5760514601932" y="296.4900582925986" z="0.0" />
    <detection t="972" x="335.23547501793826" y="296.16262884919" z="0.0" />
    <detection t="973" x="335.34510588667115" y="296.66177704272326" z="0.0" />
    <detection t="974" x="335.77106268165295" y="295.8375412778723" z="0.0" />
    <detection t="975" x="335.3642862381694" y="296.3836512716679" z="0.0" />
    <detection t="976" x="336.6018442378402" y="295.5730399038679" z="0.0" />
    <detection t="977" x="336.27212079837216" y="295.34256532645315" z="0.0" />
    <detection t="978" x="335.89435321025144" y="295.5473635034746" z="0.0" />
    <detection t="979" x="336.06313009384974" y="295.63178940645076" z="0.0" />
    <detection t="980" x="335.33538745945486" y="295.4528578071978" z="0.0" />
    <detection t="981" x="334.3841702252647" y="295.1069219391078" z="0.0" />
    <detection t="982" x="335.49835125424175" y="294.8202699532824" z="0.0" />
    <detection t="983" x="335.1094083240214" y="294.88354696964245" z="0.0" />
    <detection t="984" x="335.2067830977431" y="295.39335044737027" z="0.0" />
    <detection t="985" x="334.862648400927" y="295.140591363574" z="0.0" />
    <detection t="986" x="335.11643995915557" y="295.4143657552814" z="0.0" />
    <detection t="987" x="334.5780525624635" y="295.00227140834534" z="0.0" />
    <detection t="988" x="334.57919828524865" y="295.5313140117888" z="0.0" />
    <detection t="989" x="335.31850218314383" y="294.9653789017904" z="0.0" />
    <detection t="990" x="335.64696363234805" y="294.4882965269206" z="0.0" />
    <detection t="991" x="337.2204470272748" y="295.20565229461323" z="0.0" />
    <detection t="992" x="334.40134250439803" y="294.6405822415488" z="0.0" />
    <detection t="993" x="335.5178843338766" y="295.76632520666254" z="0.0" />
    <detection t="994" x="335.4127680178405" y="295.4658172170251" z="0.0" />
    <detection t="995" x="336.30261995666837" y="295.3974810007416" z="0.0" />
    <detection t="996" x="335.9485075035941" y="294.41497645598196" z="0.0" />
    <detection t="997" x="336.019030015289" y="295.68652941212235" z="0.0" />
    <detection t="998" x="336.514875626335" y="295.05545690154605" z="0.0" />
    <detection t="999" x="334.82428063902853" y="295.5535875206031" z="0.0" />
  </particle>
</Tracks>
